{
  "id": "neele-neele-ambar-par",
  "title": "Neele Neele Ambar Par",
  "export": true,
  "info": [
    "Film/Artist: Kalakaar",
    "Scale: F BASS/MIDDLE",
    "Source: https://www.notationsworld.com/neele-neele-ambar-par-sargam-and-flute-notes.html"
  ],
  "thumbnail": "images/neele-neele-ambar-par.jpg",
  "background": "images/neele-neele-ambar-par.jpg",
  "sections": [
    {
      "name": "STHAYI",
      "lines": [
        {
          "lyrics": "Neele neele ambar par",
          "indian": "dha Sa Ga Re Re: Ga Re ni"
        },
        {
          "lyrics": "Chand jab aaye",
          "indian": "pa ni Re Sa Sa: Re Sa dha"
        },
        {
          "lyrics": "Pyaar barsaye",
          "indian": "dha Sa Ga Re Re: Ga Re ni"
        },
        {
          "lyrics": "Humko tarsaaye",
          "indian": "pa ni Re Sa Sa: Re Sa dha"
        },
        {
          "lyrics": "Aisa koi saathi ho",
          "indian": "dha Sa Ga Sa Dha: Dha: Dha:"
        },
        {
          "lyrics": "Aisa koi premi ho",
          "indian": "ni Ga Dha Pa Pa: Pa: Pa:"
        },
        {
          "lyrics": "Pyaas dil ki bujha jaye",
          "indian": "Sa Ga Pa ma ma ma ma Ga"
        },
        {
          "lyrics": "Neele neele ambar par",
          "indian": "dha Sa Ga Re Re: Ga Re ni"
        },
        {
          "lyrics": "Chand jab aaye",
          "indian": "pa ni Re Sa Sa: Re Sa dha"
        },
        {
          "lyrics": "Pyaar barsaye",
          "indian": "dha Sa Ga Re Re: Ga Re ni"
        },
        {
          "lyrics": "Humko tarsaaye",
          "indian": "pa ni Re Sa Sa: Re Sa dha"
        },
        {
          "lyrics": "Aisa koi saathi ho",
          "indian": "dha Sa Ga Sa Dha: Dha: Dha:"
        },
        {
          "lyrics": "Aisa koi premi ho",
          "indian": "ni Ga Dha Pa Pa: Pa: Pa:"
        },
        {
          "lyrics": "Pyaas dil ki bujha jaye",
          "indian": "Sa Ga Pa ma ma ma ma Ga"
        },
        {
          "lyrics": "Neele neele ambar par",
          "indian": "dha Sa Ga Re Re: Ga Re ni"
        },
        {
          "lyrics": "Chand jab aaye",
          "indian": "pa ni Re Sa Sa: Re Sa dha"
        },
        {
          "lyrics": "Pyaar barsaye",
          "indian": "dha Sa Ga Re Re: Ga Re ni"
        },
        {
          "lyrics": "Humko tarsaaye",
          "indian": "pa ni Re Sa Sa: Re Sa dha"
        },
        {
          "lyrics": "Hoo oonche-oonche parvat jab choomte hain ambar ko",
          "indian": "Dha Dha Dha Dha Dha Dha Dha Dha Dha Ni Dha Pa Re Pa Pa"
        },
        {
          "lyrics": "Pyaasa pyaasa ambar jab choomta hai sagar ko",
          "indian": "ma ma ma ma ma ma ma ma Dha ma Ga Sa Ga Ga"
        },
        {
          "lyrics": "Hoo oonche-oonche parvat jab choomte hain ambar ko",
          "indian": "Dha Dha Dha Dha Dha Dha Dha Dha Ni Dha Pa Re Pa Pa"
        },
        {
          "lyrics": "Pyaasa pyaasa ambar jab choomta hai sagar ko",
          "indian": "ma ma ma ma ma ma ma ma Dha ma Ga Sa Ga Ga"
        },
        {
          "lyrics": "Pyaar se kasne ko",
          "indian": "dha Sa Ga Re Re: Ga Re ni"
        },
        {
          "lyrics": "Baahon mein basne ko",
          "indian": "pa ni Re Sa Sa: Re Sa dha"
        },
        {
          "lyrics": "Dil mera lalchaaye",
          "indian": "dha Sa Ga Re Re: Ga Re ni"
        },
        {
          "lyrics": "Koi toh aa jaye",
          "indian": "pa ni Re Sa Sa: Re Sa dha"
        },
        {
          "lyrics": "Aisa koi saathi ho",
          "indian": "dha Sa Ga Sa Dha: Dha: Dha:"
        },
        {
          "lyrics": "Aisa koi premi ho",
          "indian": "ni Ga Dha Pa Pa: Pa: Pa:"
        },
        {
          "lyrics": "Pyaas dil ki bujha jaye",
          "indian": "Sa Ga Pa ma ma ma ma Ga"
        },
        {
          "lyrics": "Neele neele ambar par",
          "indian": "dha Sa Ga Re Re: Ga Re ni"
        },
        {
          "lyrics": "Chand jab aaye",
          "indian": "pa ni Re Sa Sa: Re Sa dha"
        },
        {
          "lyrics": "Pyaar barsaye",
          "indian": "dha Sa Ga Re Re: Ga Re ni"
        },
        {
          "lyrics": "Humko tarsaaye",
          "indian": "pa ni Re Sa Sa: Re Sa dha"
        }
      ]
    }
  ]
}
