{
  "id": "hawa-hawa",
  "title": "Hawa Hawa",
  "export": true,
  "info": [
    "Film/Artist: Hassan Jahangir",
    "Scale: C BASS/MIDDLE",
    "Source: https://www.notationsworld.com/hawa-hawa-sargam-harmonium-and-flute-notes.html"
  ],
  "thumbnail": "",
  "background": "",
  "sections": [
    {
      "name": "STHAYI",
      "lines": [
        {
          "lyrics": "Hawa hawa eh hawa",
          "indian": "Ga Ga Sa Ga: Ga Sa Ga"
        },
        {
          "lyrics": "Khusbhoo luta day",
          "indian": "Ga Sa Re Sa Ni(k)"
        },
        {
          "lyrics": "Kahaan khuli haan khuli",
          "indian": "Ga Ga Sa Ga: Ga Sa Ga"
        },
        {
          "lyrics": "Zulf bata day",
          "indian": "Ga Sa Re Sa Ni(k)"
        },
        {
          "lyrics": "Ab uska pata day",
          "indian": "p Ni(k) Ni(k) Re Sa Ni(k)"
        },
        {
          "lyrics": "Zara mujhko bata day",
          "indian": "p.n Ni(k) Ni(k) Re Sa Ni(k)"
        },
        {
          "lyrics": "Main usse milon ga",
          "indian": "p Ni(k) Ni(k) Re Sa Ni(k)"
        },
        {
          "lyrics": "Ek bar mila day",
          "indian": "p Ni(k) Ni(k) Re Sa Ni(k)"
        },
        {
          "lyrics": "Yaar mila day",
          "indian": "Re Ni(k) Sa Ni(k) Dha(k)"
        },
        {
          "lyrics": "Dildaar mila day",
          "indian": "Dha(k) Re Ni(k) Sa Ni(k) Dha(k)"
        },
        {
          "lyrics": "Yaar mila day",
          "indian": "Re Ni(k) Sa Ni(k) Dha(k)"
        },
        {
          "lyrics": "Dildaar mila day",
          "indian": "Dha(k) Re Ni(k) Sa Ni(k) Dha(k)"
        },
        {
          "lyrics": "phir kisi ke chehray ka rang khil gaya",
          "indian": "Dha(k) Ga Ga Ga Re Sa Re Ga Re Sa Re Sa Ni(k):"
        },
        {
          "lyrics": "bichra huwa aaj koi usko mil gaya",
          "indian": "p Re Re Re Sa Ni(k) Sa Re Sa Ni(k) Sa Ni(k) Dha(k):"
        },
        {
          "lyrics": "phir kisi ke chehray ka rang khil gaya",
          "indian": "Dha(k) Ga Ga Ga Re Sa Re Ga Re Sa Re Sa Ni(k):"
        },
        {
          "lyrics": "bichra huwa aaj koi usko mil gaya",
          "indian": "p Re Re Re Sa Ni(k) Sa Re Sa Ni(k) Sa Ni(k) Dha(k):"
        },
        {
          "lyrics": "Kaise mil gaya",
          "indian": "Dha(k) Dha(k) Dha(k) Dha(k) Dha(k):"
        },
        {
          "lyrics": "Kahan mil gaya",
          "indian": "Ni(k) Ni(k) Ni(k) Ni(k) Ni(k):"
        },
        {
          "lyrics": "Humne tho dhoond liya",
          "indian": "Dha(k) Ni(k) Sa Re Re Sa Ni(k)"
        },
        {
          "lyrics": "Sara zamana",
          "indian": "Dha(k) Dha(k) Ni(k) Sa Ni(k) Dha(k):"
        },
        {
          "lyrics": "Hawa hawa eh hawa",
          "indian": "Ga Ga Sa Ga: Ga Sa Ga"
        },
        {
          "lyrics": "Khusbhoo luta day",
          "indian": "Ga Sa Re Sa Ni(k)"
        },
        {
          "lyrics": "Kahaan khuli haan khuli",
          "indian": "Ga Ga Sa Ga: Ga Sa Ga"
        },
        {
          "lyrics": "Zulf bata day",
          "indian": "Ga Sa Re Sa Ni(k)"
        },
        {
          "lyrics": "Ab uska pata day",
          "indian": "p Ni(k) Ni(k) Re Sa Ni(k)"
        },
        {
          "lyrics": "Zara mujhko bata day",
          "indian": "p.n Ni(k) Ni(k) Re Sa Ni(k)"
        },
        {
          "lyrics": "Main usse milon ga",
          "indian": "p Ni(k) Ni(k) Re Sa Ni(k)"
        },
        {
          "lyrics": "Ek bar mila day",
          "indian": "p Ni(k) Ni(k) Re Sa Ni(k)"
        },
        {
          "lyrics": "Yaar mila day",
          "indian": "Re Ni(k) Sa Ni(k) Dha(k)"
        },
        {
          "lyrics": "Dildaar mila day",
          "indian": "Dha(k) Re Ni(k) Sa Ni(k) Dha(k)"
        },
        {
          "lyrics": "Yaar mila day",
          "indian": "Re Ni(k) Sa Ni(k) Dha(k)"
        },
        {
          "lyrics": "Dildaar mila day",
          "indian": "Dha(k) Re Ni(k) Sa Ni(k) Dha(k)"
        }
      ]
    }
  ]
}
