{
  "id": "kabhi-kabhi-mere-dil-me",
  "title": "Kabhi Kabhi Mere Dil Mein",
  "export": true,
  "info": [
    "Movie: Kabhi Kabhi (1976)",
    "Lyricist: Saahir Ludhiyanvi",
    "Singer: Mukesh",
    "Music Director: Khayyam",
    "Raag: Yaman",
    "Flute: G#",
    "Source: https://notesandsargam.com/kabhi-kabhi-mere-dil-me/"
  ],
  "thumbnail": "images/kabhi-kabhi-mere-dil-me.png",
  "background": "images/kabhi-kabhi-mere-dil-me.png",
  "sections": [
    {
      "name": "MUKHDA:",
      "lines": [
        {
          "lyrics": "Kabhi | kabhi | mere | dil me",
          "indian": "Pa PaMa(T) | DhaPa...Ma(T) | Ma(T)~GaGa | Re Re | Ga"
        },
        {
          "lyrics": "khayal | aata | hai",
          "indian": "Ga~Ma(T) Ga~DhaPa | Pa...Ma(T) GaRe | GaReSa"
        },
        {
          "lyrics": "Kee | jaise | tujhko | banaya",
          "indian": "Ga | GaGa | ReRe Ga | GaRe Ga"
        },
        {
          "lyrics": "gaya | hai | mere | liye",
          "indian": "Re (Ga)ReSa | Sa | Sa~Re Re(Ga)Re Sa | Sa SaNi. DhaDha"
        },
        {
          "lyrics": "Tu | abse | pehle | sitaro | me",
          "indian": "Pa' | Ma(T) Ga Ma(T) | Pa Pa Pa | PaPa PaDha Dha(Ni)Dha | Pa"
        },
        {
          "lyrics": "bas | rahee | thi | kahee",
          "indian": "PaPa | PaMa(T) Pa... | Ma(T) | DhaPa Ma(T)Ga"
        },
        {
          "lyrics": "Tujhe | jamin pe | bulaya",
          "indian": "Ga Ga | Ga Re... | Ga | Re Re(Ga)Re Ga"
        },
        {
          "lyrics": "gaya | hai | mere | liye",
          "indian": "Re (Ga)ReSa | Sa | Sa~Re Re(Ga)Re Sa | Sa SaNi. DhaDha"
        },
        {
          "lyrics": "Kabhi | kabhi | mere | dil me",
          "indian": "Pa PaMa(T) | DhaPa...Ma(T) | Ma(T)~GaGa | Re Re | Ga"
        },
        {
          "lyrics": "khayal | aata | hai",
          "indian": "Ga~Ma(T) Ga~DhaPa | Pa...Ma(T) GaRe | GaReSa"
        }
      ]
    },
    {
      "name": "INTERLUDE :",
      "lines": [
        {
          "lyrics": "",
          "indian": "Ga... Pa Dha | Pa Dha Pa | GaRe Sa | Re Ga"
        }
      ]
    },
    {
      "name": "ANTARA 1:",
      "lines": [
        {
          "lyrics": "Kabhi | kabhi | mere | dil me",
          "indian": "Pa PaMa(T) | DhaPa...Ma(T) | Ma(T)~GaGa | Re Re | Ga"
        },
        {
          "lyrics": "khayal | aata | hai",
          "indian": "Ga~Ma(T) Ga~DhaPa | Pa...Ma(T) GaRe | GaReSa"
        },
        {
          "lyrics": "Kee | yeh | badan | yeh | nigahe",
          "indian": "Ga | Ga | Ga Re... | Ga | Ga Re... Ga"
        },
        {
          "lyrics": "meree | amanat | hain",
          "indian": "Re(Ga)Re Sa | SaSa Re (Ga)Re SaSa | Sa Ni. DhaDha"
        },
        {
          "lyrics": "Yeh | gesuo | kee",
          "indian": "Pa | Ma(T)~Ga Ma(T) Pa | Pa"
        },
        {
          "lyrics": "ghanee | chhaon | hain",
          "indian": "Pa Pa | PaDha Dha...(Ni)DhaPa | Pa"
        },
        {
          "lyrics": "meree | khatir",
          "indian": "Pa(Ma(T))Pa... | Ma(T)DhaPa Ma(T)~Ga"
        },
        {
          "lyrics": "Yeh | honth | aur | yeh | baahe",
          "indian": "Ga | Ga...Ga | Re GaGa | Ga | Re... Ga"
        },
        {
          "lyrics": "meree amanat hain",
          "indian": "Re(Ga)Re Sa | SaSa Re (Ga)Re SaSa | Sa Ni. DhaDha"
        },
        {
          "lyrics": "Kabhi | kabhi | mere | dil me",
          "indian": "Pa PaMa(T) | DhaPa...Ma(T) | Ma(T)~GaGa | Re Re | Ga"
        },
        {
          "lyrics": "khayal | aata | hai",
          "indian": "Ga~Ma(T) Ga~DhaPa | Pa...Ma(T) GaRe | GaReSa"
        }
      ]
    },
    {
      "name": "INTERLUDE :",
      "lines": [
        {
          "lyrics": "",
          "indian": "Sa Re | (Sa)Re Ga | Ga Re Sa Dha. | Sa... Re"
        },
        {
          "lyrics": "",
          "indian": "Sa' DhaDha...Sa' | Dha~Pa... | Sa'~Dha... | Dha~Sa'"
        },
        {
          "lyrics": "",
          "indian": "Sa Re | (Sa)Re Ga | Ga Re Sa Dha. | Sa"
        }
      ]
    },
    {
      "name": "ANTARA 2:",
      "lines": [
        {
          "lyrics": "Kabhi | kabhi | mere dil me",
          "indian": "Sa Sa | Ni Re | ReRe | Re | Re"
        },
        {
          "lyrics": "khayal | aata | hai",
          "indian": "ReRe Re | Re(Ga)Re Sa SaReGa | Ga"
        },
        {
          "lyrics": "Kee | jaise | bajatee | hain",
          "indian": "Ga | ReGaReGa Re Sa | SaSa Sa | Sa"
        },
        {
          "lyrics": "shehnaiya | see | raaho | me",
          "indian": "Re~Ma(T) Ma(T) Ma(T)Ma(T) | Ma(T) | Ga GaPaGa | Ga~Re"
        },
        {
          "lyrics": "MUSIC:",
          "indian": "(Re)Ga...Pa | GaRe... | Sa Dha.Sa Dha.~Sa...."
        },
        {
          "lyrics": "Kee | jaise | bajatee | hain",
          "indian": "Ga | ReGaReGa Re Sa | SaSa Sa | Sa"
        },
        {
          "lyrics": "shehnaiya | see | raaho | me",
          "indian": "Re~Ma(T) Ma(T) Ma(T)Ma(T) | Ma(T) | Ga GaPaGa | Ga~Re"
        },
        {
          "lyrics": "Suhag | rat | hain",
          "indian": "PaPa Ma(T) | Dha Dha | Dha~Pa"
        },
        {
          "lyrics": "ghunghat | utha | raha | hu | mai",
          "indian": "Pa~Sa Ni~Dha | Ni Dha Pa | Pa Pa... | Ma(T)DhaPa | Ma(T)Ga"
        },
        {
          "lyrics": "MUSIC:",
          "indian": "Sa'... Ni DhaPa | {DhaNiDhaNi}Dha Pa...Ma(T) | {DhaPaMa(T)Ga}"
        },
        {
          "lyrics": "Suhag | rat | hain",
          "indian": "PaPa Ma(T) | Dha Dha | Dha~Pa"
        },
        {
          "lyrics": "ghunghat | utha | raha | hu | mai",
          "indian": "Pa~Sa Ni~Dha | Ni Dha Pa | Pa Pa... | Ma(T)DhaPa | Ma(T)Ga"
        },
        {
          "lyrics": "Simat | rahee | hai | tu",
          "indian": "Ga GaGa | Ga Re(Ga)Re | Ga | Ga"
        },
        {
          "lyrics": "sharma | ke | apni | baaho | me",
          "indian": "Re Re(Ga)Re Ga | Re | Ga Re Sa | Sa~Re Re(Ga)Re Sa | Sa SaNi Dha(Ni)Dha"
        }
      ]
    },
    {
      "name": "ANTARA 3:",
      "lines": [
        {
          "lyrics": "Kabhi | kabhi | mere | dil me",
          "indian": "Pa PaMa(T) | DhaPa...Ma(T) | Ma(T)~GaGa | Re Re | Ga"
        },
        {
          "lyrics": "khayal | aata | hai",
          "indian": "Ga~Ma(T) Ga~DhaPa | Pa...Ma(T) GaRe | GaReSa"
        },
        {
          "lyrics": "Ke | jaise | tu | mujhe chaahegi",
          "indian": "Ga | Ga Ga | Re...Ga | Ga Ga | Re Ga...Re"
        },
        {
          "lyrics": "umra | bhar | yun | hi",
          "indian": "Re(Ga)ReSa Sa | SaRe Re(Ga)Re | Sa | Sa Ni. Dha"
        },
        {
          "lyrics": "Uthhegi | meri | taraf",
          "indian": "Pa Ma(T)~GaMa(T) | Pa Pa | Pa PaPa"
        },
        {
          "lyrics": "pyaar | ki | najar | yun | hi",
          "indian": "Pa Dha...Dha(Ni)DhaPa | Pa | Pa(Ma(T))Pa... | Ma(T)(Dha)Pa | Ma(T)~Ga"
        },
        {
          "lyrics": "Main | jaanata | hun | ke | tu",
          "indian": "Ga | Ga Ga Re...Ga | Ga | Ga | Re"
        },
        {
          "lyrics": "gair | hai | magar | yun | hi",
          "indian": "Ga...Re | GaReSa | Sa SaRe Re(Ga)Re | Sa | Sa Ni. Dha"
        },
        {
          "lyrics": "Kabhi | kabhi | mere | dil me",
          "indian": "Pa PaMa(T) | DhaPa...Ma(T) | Ma(T)~GaGa | Re Re | Ga"
        },
        {
          "lyrics": "khayal | aata | hai",
          "indian": "Ga~Ma(T) Ga~DhaPa | Pa...Ma(T) GaRe | GaReSa"
        }
      ]
    }
  ]
}
