{
  "id": "sandese-aate-hai",
  "title": "Sandese Aate Hai",
  "export": true,
  "info": [
    "Film/Artist: Border",
    "Scale: E BASS/MIDDLE",
    "Source: https://www.notationsworld.com/sandese-aate-hai-sargam-and-flute-notes.html"
  ],
  "thumbnail": "",
  "background": "",
  "sections": [
    {
      "name": "STHAYI",
      "lines": [
        {
          "lyrics": "Hooo hohohoo",
          "indian": "D: N(K).R' S'"
        },
        {
          "lyrics": "Hooo hohohoo",
          "indian": "N(K).D P: D S' N(k)"
        },
        {
          "lyrics": "Hoo hoo hoo",
          "indian": "m: P: D:"
        },
        {
          "lyrics": "Hohohoo hoo hoo",
          "indian": "m G R: P: m:"
        },
        {
          "lyrics": "Hooo hohohoo",
          "indian": "D: N(K).R' S'"
        },
        {
          "lyrics": "Hooo hohohoo",
          "indian": "N(K).D P: D S' N(k)"
        },
        {
          "lyrics": "Hoo hoo hoo",
          "indian": "m: P: D:"
        },
        {
          "lyrics": "Hohohoo hoo hoo",
          "indian": "m G R: P: m:"
        },
        {
          "lyrics": "Sandesee aate hain",
          "indian": "S S S D: P: D"
        },
        {
          "lyrics": "Humee tadpaate hain",
          "indian": "S S S D: P: D"
        },
        {
          "lyrics": "To chitthi aati hai",
          "indian": "S S S D: P: D"
        },
        {
          "lyrics": "To poochh jaati hai",
          "indian": "S S S D: P D"
        },
        {
          "lyrics": "Ke ghar kab aaonge",
          "indian": "m G S R: G S R"
        },
        {
          "lyrics": "Ke ghar kab aaonge",
          "indian": "m G S R: G S R"
        },
        {
          "lyrics": "Likho kab aaonge",
          "indian": "m G S R: G S R"
        },
        {
          "lyrics": "Ki tum bin yee ghar soona",
          "indian": "P P P P D D P P D D P"
        },
        {
          "lyrics": "Soona hai",
          "indian": "S S N(k) N(k) D"
        },
        {
          "lyrics": "Sandesee aate hain",
          "indian": "S S S D: P: D"
        },
        {
          "lyrics": "Humee tadpaate hain",
          "indian": "S S S D: P: D"
        },
        {
          "lyrics": "To chitthi aati hai",
          "indian": "S S S D: P: D"
        },
        {
          "lyrics": "To poochh jaati hai",
          "indian": "S S S D: P D"
        },
        {
          "lyrics": "Ke ghar kab aaonge",
          "indian": "m G S R: G S R"
        },
        {
          "lyrics": "Ke ghar kab aaonge",
          "indian": "m G S R: G S R"
        },
        {
          "lyrics": "Likho kab aaonge",
          "indian": "m G S R: G S R"
        },
        {
          "lyrics": "Ki tum bin yee ghar soona",
          "indian": "P P P P D D P P D D P"
        },
        {
          "lyrics": "Soona hai",
          "indian": "S S N(k) N(k) D"
        }
      ]
    }
  ]
}
