{
  "id": "sandese-aate-hai",
  "title": "Sandese Aate Hai",
  "export": true,
  "info": [
    "Film/Artist: Border",
    "Scale: E BASS/MIDDLE",
    "Source: https://www.notationsworld.com/sandese-aate-hai-sargam-and-flute-notes.html"
  ],
  "thumbnail": "",
  "background": "",
  "sections": [
    {
      "name": "STHAYI",
      "lines": [
        {
          "lyrics": "Hooo hohohoo",
          "indian": "Dha: N(K).R' Sa'"
        },
        {
          "lyrics": "Hooo hohohoo",
          "indian": "N(K).D Pa: Dha Sa' Ni(k)"
        },
        {
          "lyrics": "Hoo hoo hoo",
          "indian": "Ma: Pa: Dha:"
        },
        {
          "lyrics": "Hohohoo hoo hoo",
          "indian": "Ma Ga Re: Pa: Ma:"
        },
        {
          "lyrics": "Hooo hohohoo",
          "indian": "Dha: N(K).R' Sa'"
        },
        {
          "lyrics": "Hooo hohohoo",
          "indian": "N(K).D Pa: Dha Sa' Ni(k)"
        },
        {
          "lyrics": "Hoo hoo hoo",
          "indian": "Ma: Pa: Dha:"
        },
        {
          "lyrics": "Hohohoo hoo hoo",
          "indian": "Ma Ga Re: Pa: Ma:"
        },
        {
          "lyrics": "Sandesee aate hain",
          "indian": "Sa Sa Sa Dha: Pa: Dha"
        },
        {
          "lyrics": "Humee tadpaate hain",
          "indian": "Sa Sa Sa Dha: Pa: Dha"
        },
        {
          "lyrics": "To chitthi aati hai",
          "indian": "Sa Sa Sa Dha: Pa: Dha"
        },
        {
          "lyrics": "To poochh jaati hai",
          "indian": "Sa Sa Sa Dha: Pa Dha"
        },
        {
          "lyrics": "Ke ghar kab aaonge",
          "indian": "Ma Ga Sa Re: Ga Sa Re"
        },
        {
          "lyrics": "Ke ghar kab aaonge",
          "indian": "Ma Ga Sa Re: Ga Sa Re"
        },
        {
          "lyrics": "Likho kab aaonge",
          "indian": "Ma Ga Sa Re: Ga Sa Re"
        },
        {
          "lyrics": "Ki tum bin yee ghar soona",
          "indian": "Pa Pa Pa Pa Dha Dha Pa Pa Dha Dha Pa"
        },
        {
          "lyrics": "Soona hai",
          "indian": "Sa Sa Ni(k) Ni(k) Dha"
        },
        {
          "lyrics": "Sandesee aate hain",
          "indian": "Sa Sa Sa Dha: Pa: Dha"
        },
        {
          "lyrics": "Humee tadpaate hain",
          "indian": "Sa Sa Sa Dha: Pa: Dha"
        },
        {
          "lyrics": "To chitthi aati hai",
          "indian": "Sa Sa Sa Dha: Pa: Dha"
        },
        {
          "lyrics": "To poochh jaati hai",
          "indian": "Sa Sa Sa Dha: Pa Dha"
        },
        {
          "lyrics": "Ke ghar kab aaonge",
          "indian": "Ma Ga Sa Re: Ga Sa Re"
        },
        {
          "lyrics": "Ke ghar kab aaonge",
          "indian": "Ma Ga Sa Re: Ga Sa Re"
        },
        {
          "lyrics": "Likho kab aaonge",
          "indian": "Ma Ga Sa Re: Ga Sa Re"
        },
        {
          "lyrics": "Ki tum bin yee ghar soona",
          "indian": "Pa Pa Pa Pa Dha Dha Pa Pa Dha Dha Pa"
        },
        {
          "lyrics": "Soona hai",
          "indian": "Sa Sa Ni(k) Ni(k) Dha"
        }
      ]
    }
  ]
}
