{
  "id": "sandese-aate-hai",
  "title": "Sandese Aate Hai",
  "export": true,
  "info": [
    "Film/Artist: Border",
    "Scale: E BASS/MIDDLE",
    "Source: https://www.notationsworld.com/sandese-aate-hai-sargam-and-flute-notes.html"
  ],
  "thumbnail": "",
  "background": "",
  "sections": [
    {
      "name": "STHAYI",
      "lines": [
        {
          "lyrics": "Hooo hohohoo",
          "indian": "D: N(K).R' S'",
          "western": "A: B(K).D' C'"
        },
        {
          "lyrics": "Hooo hohohoo",
          "indian": "N(K).D P: D S' N(k)",
          "western": "B(K).A G: A C' Bb"
        },
        {
          "lyrics": "Hoo hoo hoo",
          "indian": "m: P: D:",
          "western": "F: G: A:"
        },
        {
          "lyrics": "Hohohoo hoo hoo",
          "indian": "m G R: P: m:",
          "western": "F E D: G: F:"
        },
        {
          "lyrics": "Hooo hohohoo",
          "indian": "D: N(K).R' S'",
          "western": "A: B(K).D' C'"
        },
        {
          "lyrics": "Hooo hohohoo",
          "indian": "N(K).D P: D S' N(k)",
          "western": "B(K).A G: A C' Bb"
        },
        {
          "lyrics": "Hoo hoo hoo",
          "indian": "m: P: D:",
          "western": "F: G: A:"
        },
        {
          "lyrics": "Hohohoo hoo hoo",
          "indian": "m G R: P: m:",
          "western": "F E D: G: F:"
        },
        {
          "lyrics": "Sandesee aate hain",
          "indian": "S S S D: P: D",
          "western": "C C C A: G: A"
        },
        {
          "lyrics": "Humee tadpaate hain",
          "indian": "S S S D: P: D",
          "western": "C C C A: G: A"
        },
        {
          "lyrics": "To chitthi aati hai",
          "indian": "S S S D: P: D",
          "western": "C C C A: G: A"
        },
        {
          "lyrics": "To poochh jaati hai",
          "indian": "S S S D: P D",
          "western": "C C C A: G A"
        },
        {
          "lyrics": "Ke ghar kab aaonge",
          "indian": "m G S R: G S R",
          "western": "F E C D: E C D"
        },
        {
          "lyrics": "Ke ghar kab aaonge",
          "indian": "m G S R: G S R",
          "western": "F E C D: E C D"
        },
        {
          "lyrics": "Likho kab aaonge",
          "indian": "m G S R: G S R",
          "western": "F E C D: E C D"
        },
        {
          "lyrics": "Ki tum bin yee ghar soona",
          "indian": "P P P P D D P P D D P",
          "western": "G G G G A A G G A A G"
        },
        {
          "lyrics": "Soona hai",
          "indian": "S S N(k) N(k) D",
          "western": "C C Bb Bb A"
        },
        {
          "lyrics": "Sandesee aate hain",
          "indian": "S S S D: P: D",
          "western": "C C C A: G: A"
        },
        {
          "lyrics": "Humee tadpaate hain",
          "indian": "S S S D: P: D",
          "western": "C C C A: G: A"
        },
        {
          "lyrics": "To chitthi aati hai",
          "indian": "S S S D: P: D",
          "western": "C C C A: G: A"
        },
        {
          "lyrics": "To poochh jaati hai",
          "indian": "S S S D: P D",
          "western": "C C C A: G A"
        },
        {
          "lyrics": "Ke ghar kab aaonge",
          "indian": "m G S R: G S R",
          "western": "F E C D: E C D"
        },
        {
          "lyrics": "Ke ghar kab aaonge",
          "indian": "m G S R: G S R",
          "western": "F E C D: E C D"
        },
        {
          "lyrics": "Likho kab aaonge",
          "indian": "m G S R: G S R",
          "western": "F E C D: E C D"
        },
        {
          "lyrics": "Ki tum bin yee ghar soona",
          "indian": "P P P P D D P P D D P",
          "western": "G G G G A A G G A A G"
        },
        {
          "lyrics": "Soona hai",
          "indian": "S S N(k) N(k) D",
          "western": "C C Bb Bb A"
        }
      ]
    }
  ]
}