{
  "id": "thank-you-flute-music",
  "title": "Thank You Flute Music",
  "export": true,
  "info": [
    "Source: https://www.notationsworld.com/thank-you-flute-music-sargam-harmonium-and-flute-notes.html"
  ],
  "thumbnail": "",
  "background": "",
  "sections": [
    {
      "name": "STHAYI",
      "lines": [
        {
          "lyrics": "",
          "indian": "Ga. Ga Re ma Ga. Ga Re ma Ga.",
          "western": "E. E D F E. E D F E."
        },
        {
          "lyrics": "",
          "indian": "Ga Re ma Ga. Re Sa. ni ni.",
          "western": "E D F E. D C. B. B.."
        },
        {
          "lyrics": "",
          "indian": "ni. Sa Re. Sa ni",
          "western": "B.. C D. C B."
        },
        {
          "lyrics": "",
          "indian": "dha ni Sa Re Ga. Ga Re ma Ga. Ga Re ma Ga.",
          "western": "A. B. C D E. E D F E. E D F E."
        },
        {
          "lyrics": "",
          "indian": "Ga Re ma Ga. Re Sa. ni ni.",
          "western": "E D F E. D C. B. B.."
        },
        {
          "lyrics": "",
          "indian": "ni. Sa Re. dha(k) dha",
          "western": "B.. C D. A.(k) A."
        },
        {
          "lyrics": "",
          "indian": "dha(k).dha ni Sa Re. Re Re(K).Ga Re.",
          "western": "A.(k).A. B. C D. D D(K).E D."
        },
        {
          "lyrics": "",
          "indian": "Re Ga ma Ga. Ga Ga(K).ma Ga.",
          "western": "D E F E. E E(K).F E."
        },
        {
          "lyrics": "",
          "indian": "dha(k).dha ni Sa Re. Re Re(K).Ga Re.",
          "western": "A.(k).A. B. C D. D D(K).E D."
        },
        {
          "lyrics": "",
          "indian": "Sa ni Sa Re Ga:",
          "western": "C B. C D E:"
        }
      ]
    }
  ]
}
