{
  "id": "tujh-mein-rab-dikhta-hai-sargam-harmonium-and-flute-notes",
  "title": "Tujh Mein Rab Dikhta Hai Sargam, Harmonium And Flute Notes",
  "export": true,
  "info": [
    "Scale: G# BASS/MIDDLE",
    "Source: https://www.notationsworld.com/tujh-mein-rab-dikhta-hai-sargam-and-flute-notes.html"
  ],
  "thumbnail": "images/tujh-mein-rab-dikhta-hai-sargam-harmonium-and-flute-notes.png",
  "background": "images/tujh-mein-rab-dikhta-hai-sargam-harmonium-and-flute-notes.png",
  "sections": [
    {
      "name": "STHAYI",
      "lines": [
        {
          "lyrics": "Tuu hii to jannat meerri",
          "indian": "Dha Dha Ni Pa Dha Sa' Ni"
        },
        {
          "lyrics": "Tuu hii hera junonn",
          "indian": "Ni Ni Sa' Sa' Dha Dha"
        },
        {
          "lyrics": "Tuu hii toh mannat meeri",
          "indian": "Dha Dha Ni Pa Dha Sa' Ni"
        },
        {
          "lyrics": "Tuu hii ruhh ka sukoon",
          "indian": "Ni Ni Sa' Ga' Ga' Dha Dha"
        },
        {
          "lyrics": "Tuu hii ankhiyoo ki thandak",
          "indian": "Ga' ma' Pa' Pa' ma' Ga' Re' Ga'"
        },
        {
          "lyrics": "Tuu hii dil kii hai dastak",
          "indian": "Ga' ma' Pa' Pa' ma' Ga' Re' Ga'"
        },
        {
          "lyrics": "Aurr kuch naa janoon main",
          "indian": "Ga' ma' Re' Re' Re' Ga' Sa' Sa'"
        },
        {
          "lyrics": "Bass itnaa hi janoon main",
          "indian": "Sa' Ni Re' Sa' Ni Re' Sa' Ni Sa' Ni Dha Pa"
        },
        {
          "lyrics": "Tujhh main rabb dikhtaa haii",
          "indian": "Ga Sa': Re' Sa' Ni Ni Dha Pa"
        },
        {
          "lyrics": "Yaaraa main kyaa karoon",
          "indian": "ma Sa': Sa' Re' Sa' Re' Ni Ni Dha"
        },
        {
          "lyrics": "Tujhh main rabb dikhtaa haii",
          "indian": "Ga Sa': Re' Sa' Ni Ni Dha Pa"
        },
        {
          "lyrics": "Yaaraa main kyaa karoon",
          "indian": "ma Sa': Sa' Re' Sa' Re' Ni Ni Dha"
        },
        {
          "lyrics": "Sajdee saee jhuktaa haii",
          "indian": "Dha Ga': ma' Ga' Re' Re' Sa' Ni"
        },
        {
          "lyrics": "Yaaraa main kyaa karoon",
          "indian": "Dha Sa': Sa' Re' Sa' Re' Ni Ni Dha"
        },
        {
          "lyrics": "Tujhh main rabb dikhtaa haii",
          "indian": "Ga Sa': Re' Sa' Ni Ni Dha Pa"
        },
        {
          "lyrics": "Yaaraa main kyaa karoon",
          "indian": "ma Sa': Sa' Re' Sa' Re' Ni Ni Dha"
        }
      ]
    }
  ]
}
