{
  "id": "woh-ladki-jo",
  "title": "Woh Ladki Jo",
  "export": true,
  "info": [
    "Film/Artist: Baadshah",
    "Scale: F BASS/MIDDLE",
    "Source: https://www.notationsworld.com/woh-ladki-jo-sargam-harmonium-and-flute-notes.html"
  ],
  "thumbnail": "",
  "background": "",
  "sections": [
    {
      "name": "STHAYI",
      "lines": [
        {
          "lyrics": "Kahin zulf ka baadal o ho",
          "indian": "Dha Dha Dha Dha Dha Dha Dha Pa Ni"
        },
        {
          "lyrics": "Kahin rangeen aanchal aa ha",
          "indian": "Ni Ni Dha Dha Dha Dha Dha Pa"
        },
        {
          "lyrics": "Kahin honth gulabi o ho",
          "indian": "Dha Dha Dha Dha Dha Dha Pa Ni"
        },
        {
          "lyrics": "Kahin chaal sharabi aa ha",
          "indian": "Ni Ni Dha Dha Dha Dha Dha Dha"
        },
        {
          "lyrics": "Kahin aankh mein jaadu o ho",
          "indian": "Dha Dha Dha Dha Dha Dha Re' Ni"
        },
        {
          "lyrics": "Kahin jism ki khushboo aa ha",
          "indian": "Ni Ni Dha Dha Dha Dha Dha Dha"
        },
        {
          "lyrics": "Kahin narm nigaahein o ho",
          "indian": "Dha Dha Dha Dha Dha Dha Pa Ni"
        },
        {
          "lyrics": "Kahin gori baahein aa ha",
          "indian": "Ni Ni Dha Dha Dha Dha Dha Dha"
        },
        {
          "lyrics": "Haan yahan kadam",
          "indian": "Dha: Pa Ni: Dha Sa':"
        },
        {
          "lyrics": "Kadam par lakhon",
          "indian": "Dha Ni: Ni Dha Pa: Pa:"
        },
        {
          "lyrics": "Haseenayein hai",
          "indian": "Pa Ga: Ni: Pa Dha:"
        },
        {
          "lyrics": "Hum magar yeh dil",
          "indian": "Dha: Pa Ni: Dha Sa':"
        },
        {
          "lyrics": "Ka tohfa dene",
          "indian": "Dha Ni: Ni Dha Pa: Pa:"
        },
        {
          "lyrics": "Usse aaye hai",
          "indian": "Pa Ga: Ni: Pa Dha:"
        },
        {
          "lyrics": "Woh ladki jo sabse alag hai",
          "indian": ",Dha ,Dha ,Dha Sa Ga Pa Pa Ma Ga Ma Ma Re:"
        },
        {
          "lyrics": "Woh ladki jo sabse alag hai",
          "indian": ",Pa ,Pa ,Pa ,Ni Re Ma Ma Ga Re Sa Sa Ga:"
        },
        {
          "lyrics": "Woh ladki jo sabse alag hai",
          "indian": ",Dha ,Dha ,Dha Sa Ga Pa Pa Ma Ga Ma Dha Dha Re:"
        },
        {
          "lyrics": "Woh ladki jo sabse alag hai",
          "indian": ",Pa ,Pa ,Pa ,Ni Re Ma Ma Ga Re Sa Sa Ga:"
        },
        {
          "lyrics": "Haan yahan kadam",
          "indian": "Dha: Pa Ni: Dha Sa':"
        },
        {
          "lyrics": "Kadam par lakhon",
          "indian": "Dha Ni: Ni Dha Pa: Pa:"
        },
        {
          "lyrics": "Haseenayein hai",
          "indian": "Pa Ga: Ni: Pa Dha:"
        },
        {
          "lyrics": "Hum magar yeh dil",
          "indian": "Dha: Pa Ni: Dha Sa':"
        },
        {
          "lyrics": "Ka tohfa dene",
          "indian": "Dha Ni: Ni Dha Pa: Pa:"
        },
        {
          "lyrics": "Usse aaye hai",
          "indian": "Pa Ga: Ni: Pa Dha:"
        },
        {
          "lyrics": "Woh ladki jo sabse alag hai",
          "indian": ",Dha ,Dha ,Dha Sa Ga Pa Pa Ma Ga Ma Ma Re:"
        },
        {
          "lyrics": "Woh ladki jo sabse alag hai",
          "indian": ",Pa ,Pa ,Pa ,Ni Re Ma Ma Ga Re Sa Sa Ga:"
        }
      ]
    }
  ]
}
